steamworkspy/CHANGES.md
steamworkspy/LICENSE
steamworkspy/README.md
steamworkspy/SteamworksPy64.dll
steamworkspy/__init__.py
steamworkspy/requirements.txt
steamworkspy/setup.py
steamworkspy/steam_api64.dll
steamworkspy/steam_api64.lib
steamworkspy/steamworks/__init__.py
steamworkspy/steamworks/enums.py
steamworkspy/steamworks/exceptions.py
steamworkspy/steamworks/methods.py
steamworkspy/steamworks/structs.py
steamworkspy/steamworks/util.py
steamworkspy/steamworks/interfaces/__init__.py
steamworkspy/steamworks/interfaces/apps.py
steamworkspy/steamworks/interfaces/friends.py
steamworkspy/steamworks/interfaces/matchmaking.py
steamworkspy/steamworks/interfaces/music.py
steamworkspy/steamworks/interfaces/screenshots.py
steamworkspy/steamworks/interfaces/users.py
steamworkspy/steamworks/interfaces/userstats.py
steamworkspy/steamworks/interfaces/utils.py
steamworkspy/steamworks/interfaces/workshop.py
steamworkspy-0.0.1.dist-info/METADATA
steamworkspy-0.0.1.dist-info/WHEEL
steamworkspy-0.0.1.dist-info/licenses/LICENSE
steamworkspy-0.0.1.dist-info/RECORD
