Metadata-Version: 2.3
Name: steamworkspy
Version: 0.0.1
Summary: A small example package
Project-URL: Homepage, https://github.com/RocketFriday/SteamworksPy
Project-URL: Issues, https://github.com/RocketFriday/SteamworksPy/issues
Author-email: RocketFriday <Rocket.Friday@Gmail.com>
Classifier: License :: OSI Approved :: MIT License
Classifier: Operating System :: OS Independent
Classifier: Programming Language :: Python :: 3
Requires-Python: >=3.8
